javascript/__init__.py
javascript/py.typed
alexwlchan_python_js_files-1.0.1.dist-info/LICENSE
alexwlchan_python_js_files-1.0.1.dist-info/METADATA
alexwlchan_python_js_files-1.0.1.dist-info/WHEEL
alexwlchan_python_js_files-1.0.1.dist-info/top_level.txt
alexwlchan_python_js_files-1.0.1.dist-info/RECORD
